sf_oauth/__init__.py
sf_oauth/oauth.py
sf_oauth-0.1.1.dist-info/licenses/LICENSE
sf_oauth-0.1.1.dist-info/METADATA
sf_oauth-0.1.1.dist-info/WHEEL
sf_oauth-0.1.1.dist-info/top_level.txt
sf_oauth-0.1.1.dist-info/RECORD
