Metadata-Version: 2.4
Name: sf_oauth
Version: 0.1.1
Summary: A simple OAuth client Salesforce. Connect notebooks or CLIs with a browser-based flow.
Author-email: Stephen Funk <stephenlfunk@gmail.com>
License: MIT
Keywords: salesforce,SOQL,simple-salesforce,oauth,notebook
Classifier: Programming Language :: Python :: 3
Classifier: Programming Language :: Python :: 3.10
Classifier: Programming Language :: Python :: 3.11
Classifier: Programming Language :: Python :: 3.12
Classifier: Programming Language :: Python :: 3.13
Classifier: License :: OSI Approved :: MIT License
Classifier: Operating System :: OS Independent
Classifier: Topic :: Software Development :: Libraries :: Python Modules
Classifier: Intended Audience :: Developers
Requires-Python: >=3.10
License-File: LICENSE
Requires-Dist: requests-oauthlib>=2.0.0
Provides-Extra: dev
Requires-Dist: pytest; extra == "dev"
Requires-Dist: ruff; extra == "dev"
Requires-Dist: mypy; extra == "dev"
Requires-Dist: black; extra == "dev"
Dynamic: license-file
